{
  "unpublishedPage": {
    "name": "Page1",
    "slug": "page1",
    "layouts": [
      {
        "viewMode": false,
        "dsl": {
          "widgetName": "MainContainer",
          "backgroundColor": "none",
          "rightColumn": 4896,
          "snapColumns": 64,
          "detachFromLayout": true,
          "widgetId": "0",
          "topRow": 0,
          "bottomRow": 1090,
          "containerStyle": "none",
          "snapRows": 124,
          "parentRowSpace": 1,
          "type": "CANVAS_WIDGET",
          "canExtend": true,
          "version": 89,
          "minHeight": 1292,
          "dynamicTriggerPathList": [],
          "parentColumnSpace": 1,
          "dynamicBindingPathList": [],
          "leftColumn": 0
        },
        "layoutOnLoadActions": [
          [
            {
              "id": "Page1_getRows",
              "name": "getRows",
              "confirmBeforeExecute": false,
              "pluginType": "SAAS",
              "jsonPathKeys": [],
              "timeoutInMillisecond": 10000
            }
          ],
          [
            {
              "id": "Page1_addRow",
              "name": "addRow",
              "confirmBeforeExecute": false,
              "pluginType": "SAAS",
              "jsonPathKeys": [
                "\nTable1.newRow\n"
              ],
              "timeoutInMillisecond": 10000
            }
          ]
        ],
        "layoutOnLoadActionErrors": [],
        "validOnPageLoadActions": true,
        "id": "Page1",
        "deleted": false,
        "policies": [],
        "userPermissions": []
      }
    ],
    "userPermissions": [],
    "policies": []
  },
  "deleted": false,
  "gitSyncId": "6669289ac95bb07de92caab2_f3847583-4061-4349-9a4e-357239f319d8"
}